lki/__init__.py
lki/cmdline.py
lki/config.py
lki/error.py
lki/utils.py
lki-0.5.1.dist-info/LICENSE
lki-0.5.1.dist-info/METADATA
lki-0.5.1.dist-info/WHEEL
lki-0.5.1.dist-info/entry_points.txt
lki-0.5.1.dist-info/top_level.txt
lki-0.5.1.dist-info/RECORD
