Metadata-Version: 2.1
Name: lki
Version: 0.5.1
Summary: connect Lirian's useful commands
Home-page: https://github.com/LKI/LKI
Author: Lirian Su
Author-email: liriansu@gmail.com
License: MIT License
Classifier: Development Status :: 4 - Beta
Classifier: Intended Audience :: Developers
Classifier: Topic :: Software Development :: Libraries :: Python Modules
Classifier: License :: OSI Approved :: MIT License
Classifier: Programming Language :: Python
Classifier: Programming Language :: Python :: 3
Classifier: Programming Language :: Python :: 3.7
Classifier: Programming Language :: Python :: 3.8
Classifier: Programming Language :: Python :: 3.9
Classifier: Programming Language :: Python :: 3.10
Classifier: Operating System :: OS Independent
Classifier: Operating System :: POSIX
Classifier: Operating System :: MacOS
Classifier: Operating System :: Unix
License-File: LICENSE
Requires-Dist: click (>=8.1.3)
